Workbook

Sheet Legende & Parametres
A1: Tableau de calcul des prix de revient et des marges - PROTOTYPE
A2: A partir du modele Excel fourni par Steeve (dossier CONSULTATION 26000/536/537 DN), generalise pour comparer plusieurs offres par article et pour fonctionner sur Appel d'Offres ET Consultation restreinte.
A4: Legende des couleurs
A5: Texte bleu | B5: valeur saisie a la main (hypothese ou donnee d'entree)
A6: Texte noir | B6: formule calculee automatiquement, ne pas modifier
A7: Fond jaune | B7: cellule que Steeve/l'assistante doit remplir en priorite
A9: Comment lire ce classeur
A10: 1. "Registre offres partenaires" : on enregistre ici CHAQUE offre recue (fournisseur + prestataire logistique choisi pour cette offre), un article peut avoir plusieurs offres.
A11: 2. "Calcul par offre" : une ligne par offre. On y choisit l'offre dans la liste deroulante (colonne A), tout le reste se calcule automatiquement (achat, douane, transit, marge, frais bancaires).
A12: 3. "Synthese par article" : reprend uniquement l'offre marquee "Retenue = Oui" pour chaque article -> c'est ce qui doit remonter dans le devis.
A13: 4. Les taux ci-dessous (douane, banque...) sont modifiables : si le bareme douanier ou les commissions bancaires changent, on les met a jour ICI et tout le classeur recalcule automatiquement.
A15: Parametres douane, change et banque
A16: Parametre | B16: Valeur | C16: Note / source
A17: Droit de Douane (DD) | B17: 0.2 | C17: Bareme UEMOA/CEDEAO usuel - a confirmer par categorie tarifaire avec le transitaire
A18: Redevance Statistique (RS) | B18: 0.01 | C18: Cf. feuille 'Estimation des droits de douane' du modele Steeve
A19: PCS | B19: 0.01 | C19: idem
A20: PCC | B20: 0.005 | C20: idem
A21: COSEC | B21: 0.004 | C21: idem
A22: PROMAD (optionnel) | B22: 0 | C22: Present dans 'Determination TG1' mais pas dans le calcul final utilise - laisse a 0%, a activer si applicable a la categorie
A23: BIC (optionnel) | B23: 0 | C23: idem PROMAD - a activer si applicable
A24: TVA a l'import | B24: 0.18
A25: TVA sur vente (devis/facture) | B25: 0.18 | C25: Doit rester identique au parametre deja utilise dans Parametres > Ventes de la plateforme
A26: Taux d'assurance fret (pour valeur en douane) | B26: 0.0026 | C26: Cf. 'Frais d'approche 1' (0,26%) - convention utilisee pour la valeur en douane, pas une prime reellement facturee
A27: Marge cible par defaut | B27: 0.25 | C27: Modifiable ligne par ligne dans 'Calcul par offre'
A28: Parite fixe EUR -> XOF | B28: 655.957 | C28: Parite fixe FCFA/Euro
A29: Commission bancaire TTHU | B29: 0.006 | C29: Cf. feuille 'Marge net' du modele Steeve
A30: Commission bancaire DBS | B30: 0.006 | C30: idem
A31: Minimum commission DBS (XOF) | B31: 25000 | C31: idem
A32: Taxe sur activites financieres (TAF), sur les commissions | B32: 0.17 | C32: idem
A33: Frais fixes SWIFT (XOF) | B33: 10000 | C33: idem
A34: Timbre (XOF) | B34: 20000 | C34: idem

Sheet Registre offres partenaires
A1: ID offre | B1: Article | C1: Fournisseur (marchandise) | D1: Devise | E1: Prix unitaire (devise) | F1: Cours devise (XOF) | G1: Quantite demandee | H1: Prestataire logistique (transitaire) | I1: Fret alloue (XOF) | J1: Frais de transit / prestations transitaire (XOF) | K1: Date reception offre
A2: OF-001 | B2: Onduleur 10 kVA | C2: PowerTech SARL | D2: EUR | E2: 850 | F2: =TAUX_CHANGE_EUR -> 655.957 | G2: 5 | H2: SDV Transit | I2: 450000 | J2: 380000 | K2: 2026-08-20
A3: OF-002 | B3: Onduleur 10 kVA | C3: EnerGlobal Ltd | D3: USD | E3: 900 | F3: 610 | G3: 5 | H3: Bollore Transit & Logistics | I3: 500000 | J3: 420000 | K3: 2026-08-22
A4: OF-003 | B4: Groupe electrogene 20 kVA | C4: DieselPower Africa | D4: EUR | E4: 3200 | F4: =TAUX_CHANGE_EUR -> 655.957 | G4: 2 | H4: SDV Transit | I4: 600000 | J4: 350000 | K4: 2026-08-19
A5: OF-004 | B5: Groupe electrogene 20 kVA | C5: GenSet International | D5: USD | E5: 3450 | F5: 610 | G5: 2 | H5: Maersk Logistics | I5: 650000 | J5: 400000 | K5: 2026-08-23
A7: Une ligne = une offre recue (fournisseur + transitaire associe). Un meme article peut avoir plusieurs lignes (plusieurs offres a comparer).

Sheet Calcul par offre
A1: IDENTIFICATION | E1: ACHAT | J1: TRANSPORT, ASSURANCE & DOUANE | U1: COUT DE REVIENT & MARGE CIBLE | Y1: PRIX DE VENTE (DEVIS) | AD1: FRAIS BANCAIRES & CHANGE (paiement fournisseur) | AL1: DECISION
A2: ID offre | B2: Article | C2: Fournisseur | D2: Devise | E2: Prix achat unitaire (devise) | F2: Cours devise (XOF) | G2: Quantite | H2: PA unitaire XOF | I2: PA total XOF | J2: Fret alloue | K2: Assurance (val. en douane) | L2: Valeur en douane (CAF) | M2: Droit de douane (DD) | N2: Redevance statist. (RS) | O2: PCS | P2: PCC + COSEC | Q2: Base TVA import | R2: TVA a l'import | S2: Total droits & taxes douane | T2: Frais de transit (transitaire) | U2: COUT DE REVIENT HT | V2: Marge cible % | W2: Marge brute (valeur) | X2: Prix de vente total HT | Y2: Prix unitaire HT | Z2: Prix unitaire arrondi | AA2: Montant total arrondi HT | AB2: TVA vente (18%) | AC2: TOTAL TTC | AD2: Montant a transferer fournisseur (XOF) | AE2: Commission TTHU | AF2: Commission DBS | AG2: TAF / DBS | AH2: SWIFT | AI2: TAF / SWIFT | AJ2: Timbre | AK2: TOTAL frais bancaires & change | AL2: MARGE NETTE REELLE (valeur) | AM2: Marge nette reelle (%) | AN2: Retenue ? | AO2: (cle si retenue)
A3: OF-001 | B3: =IFERROR(INDEX('Registre offres partenaires'!$B:$B,MATCH($A3,'Registre offres partenaires'!$A:$A,0)),"") -> Onduleur 10 kVA | C3: =IFERROR(INDEX('Registre offres partenaires'!$C:$C,MATCH($A3,'Registre offres partenaires'!$A:$A,0)),"") -> PowerTech SARL | D3: =IFERROR(INDEX('Registre offres partenaires'!$D:$D,MATCH($A3,'Registre offres partenaires'!$A:$A,0)),"") -> EUR | E3: =IFERROR(INDEX('Registre offres partenaires'!$E:$E,MATCH($A3,'Registre offres partenaires'!$A:$A,0)),"") -> 850 | F3: =IFERROR(INDEX('Registre offres partenaires'!$F:$F,MATCH($A3,'Registre offres partenaires'!$A:$A,0)),"") -> 655.957 | G3: =IFERROR(INDEX('Registre offres partenaires'!$G:$G,MATCH($A3,'Registre offres partenaires'!$A:$A,0)),"") -> 5 | H3: =IFERROR(E3*F3,"") -> 557563.45 | I3: =IFERROR(H3*G3,"") -> 2787817.2 | J3: =IFERROR(INDEX('Registre offres partenaires'!$I:$I,MATCH($A3,'Registre offres partenaires'!$A:$A,0)),"") -> 450000 | K3: =IFERROR(TAUX_ASSURANCE*(I3+J3),"") -> 8418.3249 | L3: =IFERROR(I3+J3+K3,"") -> 3246235.6 | M3: =IFERROR(L3*TAUX_DD,"") -> 649247.11 | N3: =IFERROR(L3*TAUX_RS,"") -> 32462.356 | O3: =IFERROR(L3*TAUX_PCS,"") -> 32462.356 | P3: =IFERROR(L3*(TAUX_PCC+TAUX_COSEC),"") -> 29216.12 | Q3: =IFERROR(L3+M3+N3+O3+P3,"") -> 3989623.5 | R3: =IFERROR(Q3*TAUX_TVA_DOUANE,"") -> 718132.23 | S3: =IFERROR(M3+N3+O3+P3+R3,"") -> 1461520.2 | T3: =IFERROR(INDEX('Registre offres partenaires'!$J:$J,MATCH($A3,'Registre offres partenaires'!$A:$A,0)),"") -> 380000 | U3: =IFERROR(I3+J3+S3+T3,"") -> 5079337.4 | V3: =TAUX_MARGE_CIBLE -> 0.25 | W3: =IFERROR(U3*V3,"") -> 1269834.4 | X3: =IFERROR(U3+W3,"") -> 6349171.8 | Y3: =IFERROR(X3/G3,"") -> 1269834.4 | Z3: =IFERROR(ROUNDUP(Y3,-2),"") -> 1269900 | AA3: =IFERROR(Z3*G3,"") -> 6349500 | AB3: =IFERROR(AA3*TAUX_TVA_VENTE,"") -> 1142910 | AC3: =IFERROR(AA3+AB3,"") -> 7492410 | AD3: =IFERROR(I3,"") -> 2787817.2 | AE3: =IFERROR(AD3*TAUX_COMMISSION_TTHU,"") -> 16726.904 | AF3: =IFERROR(MAX(AD3*TAUX_COMMISSION_DBS,COMMISSION_DBS_MIN),"") -> 25000 | AG3: =IFERROR(AF3*TAUX_TAF,"") -> 4250 | AH3: =FORFAIT_SWIFT -> 10000 | AI3: =IFERROR(AH3*TAUX_TAF,"") -> 1700 | AJ3: =FORFAIT_TIMBRE -> 20000 | AK3: =IFERROR(SUM(AE3:AJ3),"") -> 77676.904 | AL3: =IFERROR(W3-AK3,"") -> 1192157.5 | AM3: =IFERROR(AL3/U3,"") -> 0.23470728 | AN3: Non | AO3: =IF(AN3="Oui",B3,"")
A4: OF-002 | B4: =IFERROR(INDEX('Registre offres partenaires'!$B:$B,MATCH($A4,'Registre offres partenaires'!$A:$A,0)),"") -> Onduleur 10 kVA | C4: =IFERROR(INDEX('Registre offres partenaires'!$C:$C,MATCH($A4,'Registre offres partenaires'!$A:$A,0)),"") -> EnerGlobal Ltd | D4: =IFERROR(INDEX('Registre offres partenaires'!$D:$D,MATCH($A4,'Registre offres partenaires'!$A:$A,0)),"") -> USD | E4: =IFERROR(INDEX('Registre offres partenaires'!$E:$E,MATCH($A4,'Registre offres partenaires'!$A:$A,0)),"") -> 900 | F4: =IFERROR(INDEX('Registre offres partenaires'!$F:$F,MATCH($A4,'Registre offres partenaires'!$A:$A,0)),"") -> 610 | G4: =IFERROR(INDEX('Registre offres partenaires'!$G:$G,MATCH($A4,'Registre offres partenaires'!$A:$A,0)),"") -> 5 | H4: =IFERROR(E4*F4,"") -> 549000 | I4: =IFERROR(H4*G4,"") -> 2745000 | J4: =IFERROR(INDEX('Registre offres partenaires'!$I:$I,MATCH($A4,'Registre offres partenaires'!$A:$A,0)),"") -> 500000 | K4: =IFERROR(TAUX_ASSURANCE*(I4+J4),"") -> 8437 | L4: =IFERROR(I4+J4+K4,"") -> 3253437 | M4: =IFERROR(L4*TAUX_DD,"") -> 650687.4 | N4: =IFERROR(L4*TAUX_RS,"") -> 32534.37 | O4: =IFERROR(L4*TAUX_PCS,"") -> 32534.37 | P4: =IFERROR(L4*(TAUX_PCC+TAUX_COSEC),"") -> 29280.933 | Q4: =IFERROR(L4+M4+N4+O4+P4,"") -> 3998474.1 | R4: =IFERROR(Q4*TAUX_TVA_DOUANE,"") -> 719725.33 | S4: =IFERROR(M4+N4+O4+P4+R4,"") -> 1464762.4 | T4: =IFERROR(INDEX('Registre offres partenaires'!$J:$J,MATCH($A4,'Registre offres partenaires'!$A:$A,0)),"") -> 420000 | U4: =IFERROR(I4+J4+S4+T4,"") -> 5129762.4 | V4: =TAUX_MARGE_CIBLE -> 0.25 | W4: =IFERROR(U4*V4,"") -> 1282440.6 | X4: =IFERROR(U4+W4,"") -> 6412203 | Y4: =IFERROR(X4/G4,"") -> 1282440.6 | Z4: =IFERROR(ROUNDUP(Y4,-2),"") -> 1282500 | AA4: =IFERROR(Z4*G4,"") -> 6412500 | AB4: =IFERROR(AA4*TAUX_TVA_VENTE,"") -> 1154250 | AC4: =IFERROR(AA4+AB4,"") -> 7566750 | AD4: =IFERROR(I4,"") -> 2745000 | AE4: =IFERROR(AD4*TAUX_COMMISSION_TTHU,"") -> 16470 | AF4: =IFERROR(MAX(AD4*TAUX_COMMISSION_DBS,COMMISSION_DBS_MIN),"") -> 25000 | AG4: =IFERROR(AF4*TAUX_TAF,"") -> 4250 | AH4: =FORFAIT_SWIFT -> 10000 | AI4: =IFERROR(AH4*TAUX_TAF,"") -> 1700 | AJ4: =FORFAIT_TIMBRE -> 20000 | AK4: =IFERROR(SUM(AE4:AJ4),"") -> 77420 | AL4: =IFERROR(W4-AK4,"") -> 1205020.6 | AM4: =IFERROR(AL4/U4,"") -> 0.23490768 | AN4: Oui | AO4: =IF(AN4="Oui",B4,"") -> Onduleur 10 kVA
A5: OF-003 | B5: =IFERROR(INDEX('Registre offres partenaires'!$B:$B,MATCH($A5,'Registre offres partenaires'!$A:$A,0)),"") -> Groupe electrogene 20 kVA | C5: =IFERROR(INDEX('Registre offres partenaires'!$C:$C,MATCH($A5,'Registre offres partenaires'!$A:$A,0)),"") -> DieselPower Africa | D5: =IFERROR(INDEX('Registre offres partenaires'!$D:$D,MATCH($A5,'Registre offres partenaires'!$A:$A,0)),"") -> EUR | E5: =IFERROR(INDEX('Registre offres partenaires'!$E:$E,MATCH($A5,'Registre offres partenaires'!$A:$A,0)),"") -> 3200 | F5: =IFERROR(INDEX('Registre offres partenaires'!$F:$F,MATCH($A5,'Registre offres partenaires'!$A:$A,0)),"") -> 655.957 | G5: =IFERROR(INDEX('Registre offres partenaires'!$G:$G,MATCH($A5,'Registre offres partenaires'!$A:$A,0)),"") -> 2 | H5: =IFERROR(E5*F5,"") -> 2099062.4 | I5: =IFERROR(H5*G5,"") -> 4198124.8 | J5: =IFERROR(INDEX('Registre offres partenaires'!$I:$I,MATCH($A5,'Registre offres partenaires'!$A:$A,0)),"") -> 600000 | K5: =IFERROR(TAUX_ASSURANCE*(I5+J5),"") -> 12475.124 | L5: =IFERROR(I5+J5+K5,"") -> 4810599.9 | M5: =IFERROR(L5*TAUX_DD,"") -> 962119.98 | N5: =IFERROR(L5*TAUX_RS,"") -> 48105.999 | O5: =IFERROR(L5*TAUX_PCS,"") -> 48105.999 | P5: =IFERROR(L5*(TAUX_PCC+TAUX_COSEC),"") -> 43295.399 | Q5: =IFERROR(L5+M5+N5+O5+P5,"") -> 5912227.3 | R5: =IFERROR(Q5*TAUX_TVA_DOUANE,"") -> 1064200.9 | S5: =IFERROR(M5+N5+O5+P5+R5,"") -> 2165828.3 | T5: =IFERROR(INDEX('Registre offres partenaires'!$J:$J,MATCH($A5,'Registre offres partenaires'!$A:$A,0)),"") -> 350000 | U5: =IFERROR(I5+J5+S5+T5,"") -> 7313953.1 | V5: =TAUX_MARGE_CIBLE -> 0.25 | W5: =IFERROR(U5*V5,"") -> 1828488.3 | X5: =IFERROR(U5+W5,"") -> 9142441.4 | Y5: =IFERROR(X5/G5,"") -> 4571220.7 | Z5: =IFERROR(ROUNDUP(Y5,-2),"") -> 4571300 | AA5: =IFERROR(Z5*G5,"") -> 9142600 | AB5: =IFERROR(AA5*TAUX_TVA_VENTE,"") -> 1645668 | AC5: =IFERROR(AA5+AB5,"") -> 10788268 | AD5: =IFERROR(I5,"") -> 4198124.8 | AE5: =IFERROR(AD5*TAUX_COMMISSION_TTHU,"") -> 25188.749 | AF5: =IFERROR(MAX(AD5*TAUX_COMMISSION_DBS,COMMISSION_DBS_MIN),"") -> 25188.749 | AG5: =IFERROR(AF5*TAUX_TAF,"") -> 4282.0873 | AH5: =FORFAIT_SWIFT -> 10000 | AI5: =IFERROR(AH5*TAUX_TAF,"") -> 1700 | AJ5: =FORFAIT_TIMBRE -> 20000 | AK5: =IFERROR(SUM(AE5:AJ5),"") -> 86359.585 | AL5: =IFERROR(W5-AK5,"") -> 1742128.7 | AM5: =IFERROR(AL5/U5,"") -> 0.23819249 | AN5: Non | AO5: =IF(AN5="Oui",B5,"")
A6: OF-004 | B6: =IFERROR(INDEX('Registre offres partenaires'!$B:$B,MATCH($A6,'Registre offres partenaires'!$A:$A,0)),"") -> Groupe electrogene 20 kVA | C6: =IFERROR(INDEX('Registre offres partenaires'!$C:$C,MATCH($A6,'Registre offres partenaires'!$A:$A,0)),"") -> GenSet International | D6: =IFERROR(INDEX('Registre offres partenaires'!$D:$D,MATCH($A6,'Registre offres partenaires'!$A:$A,0)),"") -> USD | E6: =IFERROR(INDEX('Registre offres partenaires'!$E:$E,MATCH($A6,'Registre offres partenaires'!$A:$A,0)),"") -> 3450 | F6: =IFERROR(INDEX('Registre offres partenaires'!$F:$F,MATCH($A6,'Registre offres partenaires'!$A:$A,0)),"") -> 610 | G6: =IFERROR(INDEX('Registre offres partenaires'!$G:$G,MATCH($A6,'Registre offres partenaires'!$A:$A,0)),"") -> 2 | H6: =IFERROR(E6*F6,"") -> 2104500 | I6: =IFERROR(H6*G6,"") -> 4209000 | J6: =IFERROR(INDEX('Registre offres partenaires'!$I:$I,MATCH($A6,'Registre offres partenaires'!$A:$A,0)),"") -> 650000 | K6: =IFERROR(TAUX_ASSURANCE*(I6+J6),"") -> 12633.4 | L6: =IFERROR(I6+J6+K6,"") -> 4871633.4 | M6: =IFERROR(L6*TAUX_DD,"") -> 974326.68 | N6: =IFERROR(L6*TAUX_RS,"") -> 48716.334 | O6: =IFERROR(L6*TAUX_PCS,"") -> 48716.334 | P6: =IFERROR(L6*(TAUX_PCC+TAUX_COSEC),"") -> 43844.701 | Q6: =IFERROR(L6+M6+N6+O6+P6,"") -> 5987237.4 | R6: =IFERROR(Q6*TAUX_TVA_DOUANE,"") -> 1077702.7 | S6: =IFERROR(M6+N6+O6+P6+R6,"") -> 2193306.8 | T6: =IFERROR(INDEX('Registre offres partenaires'!$J:$J,MATCH($A6,'Registre offres partenaires'!$A:$A,0)),"") -> 400000 | U6: =IFERROR(I6+J6+S6+T6,"") -> 7452306.8 | V6: =TAUX_MARGE_CIBLE -> 0.25 | W6: =IFERROR(U6*V6,"") -> 1863076.7 | X6: =IFERROR(U6+W6,"") -> 9315383.5 | Y6: =IFERROR(X6/G6,"") -> 4657691.7 | Z6: =IFERROR(ROUNDUP(Y6,-2),"") -> 4657700 | AA6: =IFERROR(Z6*G6,"") -> 9315400 | AB6: =IFERROR(AA6*TAUX_TVA_VENTE,"") -> 1676772 | AC6: =IFERROR(AA6+AB6,"") -> 10992172 | AD6: =IFERROR(I6,"") -> 4209000 | AE6: =IFERROR(AD6*TAUX_COMMISSION_TTHU,"") -> 25254 | AF6: =IFERROR(MAX(AD6*TAUX_COMMISSION_DBS,COMMISSION_DBS_MIN),"") -> 25254 | AG6: =IFERROR(AF6*TAUX_TAF,"") -> 4293.18 | AH6: =FORFAIT_SWIFT -> 10000 | AI6: =IFERROR(AH6*TAUX_TAF,"") -> 1700 | AJ6: =FORFAIT_TIMBRE -> 20000 | AK6: =IFERROR(SUM(AE6:AJ6),"") -> 86501.18 | AL6: =IFERROR(W6-AK6,"") -> 1776575.5 | AM6: =IFERROR(AL6/U6,"") -> 0.2383927 | AN6: Oui | AO6: =IF(AN6="Oui",B6,"") -> Groupe electrogene 20 kVA

Sheet Synthese par article
A1: Article | B1: Fournisseur retenu | C1: Quantite | D1: Prix unitaire arrondi HT | E1: Montant total HT | F1: TVA (18%) | G1: TOTAL TTC | H1: Marge nette reelle | I1: Marge nette reelle (%)
A2: Onduleur 10 kVA | B2: =IFERROR(INDEX('Calcul par offre'!$C$3:$C$6,MATCH($A2,'Calcul par offre'!$AO$3:$AO$6,0)),"(aucune offre retenue)") -> EnerGlobal Ltd | C2: =IFERROR(INDEX('Calcul par offre'!$G$3:$G$6,MATCH($A2,'Calcul par offre'!$AO$3:$AO$6,0)),"") -> 5 | D2: =IFERROR(INDEX('Calcul par offre'!$Z$3:$Z$6,MATCH($A2,'Calcul par offre'!$AO$3:$AO$6,0)),"") -> 1282500 | E2: =IFERROR(INDEX('Calcul par offre'!$AA$3:$AA$6,MATCH($A2,'Calcul par offre'!$AO$3:$AO$6,0)),"") -> 6412500 | F2: =IFERROR(INDEX('Calcul par offre'!$AB$3:$AB$6,MATCH($A2,'Calcul par offre'!$AO$3:$AO$6,0)),"") -> 1154250 | G2: =IFERROR(INDEX('Calcul par offre'!$AC$3:$AC$6,MATCH($A2,'Calcul par offre'!$AO$3:$AO$6,0)),"") -> 7566750 | H2: =IFERROR(INDEX('Calcul par offre'!$AL$3:$AL$6,MATCH($A2,'Calcul par offre'!$AO$3:$AO$6,0)),"") -> 1205020.6 | I2: =IFERROR(INDEX('Calcul par offre'!$AM$3:$AM$6,MATCH($A2,'Calcul par offre'!$AO$3:$AO$6,0)),"") -> 0.23490768
A3: Groupe electrogene 20 kVA | B3: =IFERROR(INDEX('Calcul par offre'!$C$3:$C$6,MATCH($A3,'Calcul par offre'!$AO$3:$AO$6,0)),"(aucune offre retenue)") -> GenSet International | C3: =IFERROR(INDEX('Calcul par offre'!$G$3:$G$6,MATCH($A3,'Calcul par offre'!$AO$3:$AO$6,0)),"") -> 2 | D3: =IFERROR(INDEX('Calcul par offre'!$Z$3:$Z$6,MATCH($A3,'Calcul par offre'!$AO$3:$AO$6,0)),"") -> 4657700 | E3: =IFERROR(INDEX('Calcul par offre'!$AA$3:$AA$6,MATCH($A3,'Calcul par offre'!$AO$3:$AO$6,0)),"") -> 9315400 | F3: =IFERROR(INDEX('Calcul par offre'!$AB$3:$AB$6,MATCH($A3,'Calcul par offre'!$AO$3:$AO$6,0)),"") -> 1676772 | G3: =IFERROR(INDEX('Calcul par offre'!$AC$3:$AC$6,MATCH($A3,'Calcul par offre'!$AO$3:$AO$6,0)),"") -> 10992172 | H3: =IFERROR(INDEX('Calcul par offre'!$AL$3:$AL$6,MATCH($A3,'Calcul par offre'!$AO$3:$AO$6,0)),"") -> 1776575.5 | I3: =IFERROR(INDEX('Calcul par offre'!$AM$3:$AM$6,MATCH($A3,'Calcul par offre'!$AO$3:$AO$6,0)),"") -> 0.2383927
A5: Pour qu'un article apparaisse ici, il faut qu'une de ses offres, dans "Calcul par offre", ait "Retenue" = Oui. Cette liste (colonne A) doit reprendre exactement les articles du devis en cours.
